policytools/__init__.py
policytools/action_expander.py
policytools/policy.py
policytools/policy_scp_judgment.py
policytools/service_control_policy.py
policytools/data/policies-gen.json.js
policytools/iamapi/README.md
policytools/iamapi/__init__.py
policytools/iamapi/check_response.py
policytools/iamapi/judged_action.py
policytools/iamapi/policy_checker.py
policytools/iamapi/__pycache__/__init__.cpython-37.pyc
policytools/iamapi/__pycache__/check_response.cpython-37.pyc
policytools/iamapi/__pycache__/judged_action.cpython-37.pyc
policytools/iamapi/__pycache__/policy_checker.cpython-37.pyc
policytools/master_list/__init__.py
policytools/master_list/actions_master_list_base.py
policytools/master_list/policy_gen_actions_master_list.py
policytools/master_list/__pycache__/__init__.cpython-37.pyc
policytools/master_list/__pycache__/actions_master_list_base.cpython-37.pyc
policytools/master_list/__pycache__/policy_gen_actions_master_list.cpython-37.pyc
tests/__init__.py
tests/test_action_expander.py
tests/test_policy.py
tests/test_service_control_policy.py
tests/utils.py
tests/iamapi/__init__.py
tests/iamapi/aws_client_stub.py
tests/iamapi/test_policy_checker.py
policytools-0.2.5.dist-info/LICENSE.txt
policytools-0.2.5.dist-info/METADATA
policytools-0.2.5.dist-info/WHEEL
policytools-0.2.5.dist-info/top_level.txt
policytools-0.2.5.dist-info/RECORD
