Metadata-Version: 2.1
Name: policytools
Version: 0.2.5
Summary: IAM policy tools
Home-page: https://github.com/samkeen/policy-tools
Author: samkeen
Author-email: sam.sjk@gmail.com
License: Apache License, Version 2.0
Platform: UNKNOWN
Classifier: Programming Language :: Python :: 3
Classifier: License :: OSI Approved :: Apache Software License
Classifier: Operating System :: OS Independent
Requires-Dist: pyyaml
Requires-Dist: boto3
